Websential/__init__.py
Websential/detect.py
Websential/filter.py
websential-0.1.0.dist-info/licenses/LICENCE
websential-0.1.0.dist-info/METADATA
websential-0.1.0.dist-info/WHEEL
websential-0.1.0.dist-info/top_level.txt
websential-0.1.0.dist-info/RECORD
