Metadata-Version: 2.4
Name: websential
Version: 0.1.0
Summary: Advanced Python library for website URL discovery, security protection detection, database identification, and URL classification.
Author: 0xSPARK
Author-email: HabibSarkisofficial@gmail.com
Keywords: web security,web scraping,URL detection,database detection,WAF,Cloudflare,reCAPTCHA
Classifier: Programming Language :: Python :: 3
Classifier: License :: OSI Approved :: MIT License
Classifier: Operating System :: OS Independent
Classifier: Topic :: Security
Classifier: Topic :: Internet :: WWW/HTTP
Classifier: Intended Audience :: Developers
Classifier: Intended Audience :: Information Technology
Requires-Python: >=3.8
License-File: LICENCE
Requires-Dist: requests
Requires-Dist: beautifulsoup4
Dynamic: author
Dynamic: author-email
Dynamic: classifier
Dynamic: description
Dynamic: description-content-type
Dynamic: keywords
Dynamic: license-file
Dynamic: requires-dist
Dynamic: requires-python
Dynamic: summary
